fifo/generated/syncFifo.v
module syncFifo(
  input        clock,
  input        reset,
  output       io_WriteInterface_ready,
  input        io_WriteInterface_valid,
  input  [7:0] io_WriteInterface_bits,
  input        io_ReadInterface_ready,
  output       io_ReadInterface_valid,
  output [7:0] io_ReadInterface_bits,
  output       io_full,
  output       io_empty,
  output [3:0] io_cnt
);
`ifdef RANDOMIZE_REG_INIT
  reg [31:0] _RAND_0;
  reg [31:0] _RAND_1;
  reg [31:0] _RAND_2;
  reg [31:0] _RAND_3;
  reg [31:0] _RAND_4;
  reg [31:0] _RAND_5;
  reg [31:0] _RAND_6;
  reg [31:0] _RAND_7;
  reg [31:0] _RAND_8;
  reg [31:0] _RAND_9;
  reg [31:0] _RAND_10;
  reg [31:0] _RAND_11;
`endif // RANDOMIZE_REG_INIT
  reg [7:0] memReg_0; // @[fifo.scala 42:24]
  reg [7:0] memReg_1; // @[fifo.scala 42:24]
  reg [7:0] memReg_2; // @[fifo.scala 42:24]
  reg [7:0] memReg_3; // @[fifo.scala 42:24]
  reg [7:0] memReg_4; // @[fifo.scala 42:24]
  reg [7:0] memReg_5; // @[fifo.scala 42:24]
  reg [7:0] memReg_6; // @[fifo.scala 42:24]
  reg [7:0] memReg_7; // @[fifo.scala 42:24]
  reg [7:0] memReg_8; // @[fifo.scala 42:24]
  reg [7:0] memReg_9; // @[fifo.scala 42:24]
  reg [4:0] wrptr; // @[fifo.scala 29:29]
  wire  _wrptr_cntReg_T_2 = wrptr[4] + 1'h1; // @[fifo.scala 32:49]
  wire [4:0] _wrptr_cntReg_T_3 = {_wrptr_cntReg_T_2,4'h0}; // @[Cat.scala 31:58]
  wire [4:0] _wrptr_cntReg_T_5 = wrptr + 5'h1; // @[fifo.scala 34:34]
  wire  wen = io_WriteInterface_valid & io_WriteInterface_ready; // @[fifo.scala 59:45]
  reg [4:0] rdptr; // @[fifo.scala 29:29]
  wire  _rdptr_cntReg_T_2 = rdptr[4] + 1'h1; // @[fifo.scala 32:49]
  wire [4:0] _rdptr_cntReg_T_3 = {_rdptr_cntReg_T_2,4'h0}; // @[Cat.scala 31:58]
  wire [4:0] _rdptr_cntReg_T_5 = rdptr + 5'h1; // @[fifo.scala 34:34]
  wire  ren = io_ReadInterface_valid & io_ReadInterface_ready; // @[fifo.scala 60:45]
  wire  _io_cnt_T_2 = wrptr[4] == rdptr[4]; // @[fifo.scala 47:45]
  wire  _GEN_4 = _io_cnt_T_2 ? 1'h0 : 1'h1; // @[fifo.scala 51:50 52:16 54:16]
  wire [7:0] _GEN_26 = 4'h1 == rdptr[3:0] ? memReg_1 : memReg_0; // @[fifo.scala 66:{31,31}]
  wire [7:0] _GEN_27 = 4'h2 == rdptr[3:0] ? memReg_2 : _GEN_26; // @[fifo.scala 66:{31,31}]
  wire [7:0] _GEN_28 = 4'h3 == rdptr[3:0] ? memReg_3 : _GEN_27; // @[fifo.scala 66:{31,31}]
  wire [7:0] _GEN_29 = 4'h4 == rdptr[3:0] ? memReg_4 : _GEN_28; // @[fifo.scala 66:{31,31}]
  wire [7:0] _GEN_30 = 4'h5 == rdptr[3:0] ? memReg_5 : _GEN_29; // @[fifo.scala 66:{31,31}]
  wire [7:0] _GEN_31 = 4'h6 == rdptr[3:0] ? memReg_6 : _GEN_30; // @[fifo.scala 66:{31,31}]
  wire [7:0] _GEN_32 = 4'h7 == rdptr[3:0] ? memReg_7 : _GEN_31; // @[fifo.scala 66:{31,31}]
  wire [7:0] _GEN_33 = 4'h8 == rdptr[3:0] ? memReg_8 : _GEN_32; // @[fifo.scala 66:{31,31}]
  wire [7:0] _GEN_34 = 4'h9 == rdptr[3:0] ? memReg_9 : _GEN_33; // @[fifo.scala 66:{31,31}]
  assign io_WriteInterface_ready = ~io_full; // @[fifo.scala 56:32]
  assign io_ReadInterface_valid = ~io_empty; // @[fifo.scala 57:32]
  assign io_ReadInterface_bits = ren ? _GEN_34 : 8'h0; // @[fifo.scala 65:14 64:26 66:31]
  assign io_full = io_cnt == 4'h9; // @[fifo.scala 40:29]
  assign io_empty = io_cnt == 4'h0; // @[fifo.scala 41:29]
  assign io_cnt = {{3'd0}, _GEN_4};
  always @(posedge clock) begin
    if (wen) begin // @[fifo.scala 61:14]
      if (4'h0 == wrptr[3:0]) begin // @[fifo.scala 62:23]
        memReg_0 <= io_WriteInterface_bits; // @[fifo.scala 62:23]
      end
    end
    if (wen) begin // @[fifo.scala 61:14]
      if (4'h1 == wrptr[3:0]) begin // @[fifo.scala 62:23]
        memReg_1 <= io_WriteInterface_bits; // @[fifo.scala 62:23]
      end
    end
    if (wen) begin // @[fifo.scala 61:14]
      if (4'h2 == wrptr[3:0]) begin // @[fifo.scala 62:23]
        memReg_2 <= io_WriteInterface_bits; // @[fifo.scala 62:23]
      end
    end
    if (wen) begin // @[fifo.scala 61:14]
      if (4'h3 == wrptr[3:0]) begin // @[fifo.scala 62:23]
        memReg_3 <= io_WriteInterface_bits; // @[fifo.scala 62:23]
      end
    end
    if (wen) begin // @[fifo.scala 61:14]
      if (4'h4 == wrptr[3:0]) begin // @[fifo.scala 62:23]
        memReg_4 <= io_WriteInterface_bits; // @[fifo.scala 62:23]
      end
    end
    if (wen) begin // @[fifo.scala 61:14]
      if (4'h5 == wrptr[3:0]) begin // @[fifo.scala 62:23]
        memReg_5 <= io_WriteInterface_bits; // @[fifo.scala 62:23]
      end
    end
    if (wen) begin // @[fifo.scala 61:14]
      if (4'h6 == wrptr[3:0]) begin // @[fifo.scala 62:23]
        memReg_6 <= io_WriteInterface_bits; // @[fifo.scala 62:23]
      end
    end
    if (wen) begin // @[fifo.scala 61:14]
      if (4'h7 == wrptr[3:0]) begin // @[fifo.scala 62:23]
        memReg_7 <= io_WriteInterface_bits; // @[fifo.scala 62:23]
      end
    end
    if (wen) begin // @[fifo.scala 61:14]
      if (4'h8 == wrptr[3:0]) begin // @[fifo.scala 62:23]
        memReg_8 <= io_WriteInterface_bits; // @[fifo.scala 62:23]
      end
    end
    if (wen) begin // @[fifo.scala 61:14]
      if (4'h9 == wrptr[3:0]) begin // @[fifo.scala 62:23]
        memReg_9 <= io_WriteInterface_bits; // @[fifo.scala 62:23]
      end
    end
    if (reset) begin // @[fifo.scala 29:29]
      wrptr <= 5'h0; // @[fifo.scala 29:29]
    end else if (wen) begin // @[fifo.scala 30:17]
      if (wrptr[3:0] == 4'h9) begin // @[fifo.scala 31:54]
        wrptr <= _wrptr_cntReg_T_3; // @[fifo.scala 32:24]
      end else begin
        wrptr <= _wrptr_cntReg_T_5; // @[fifo.scala 34:24]
      end
    end
    if (reset) begin // @[fifo.scala 29:29]
      rdptr <= 5'h0; // @[fifo.scala 29:29]
    end else if (ren) begin // @[fifo.scala 30:17]
      if (rdptr[3:0] == 4'h9) begin // @[fifo.scala 31:54]
        rdptr <= _rdptr_cntReg_T_3; // @[fifo.scala 32:24]
      end else begin
        rdptr <= _rdptr_cntReg_T_5; // @[fifo.scala 34:24]
      end
    end
  end
// Register and memory initialization
`ifdef RANDOMIZE_GARBAGE_ASSIGN
`define RANDOMIZE
`endif
`ifdef RANDOMIZE_INVALID_ASSIGN
`define RANDOMIZE
`endif
`ifdef RANDOMIZE_REG_INIT
`define RANDOMIZE
`endif
`ifdef RANDOMIZE_MEM_INIT
`define RANDOMIZE
`endif
`ifndef RANDOM
`define RANDOM $random
`endif
`ifdef RANDOMIZE_MEM_INIT
  integer initvar;
`endif
`ifndef SYNTHESIS
`ifdef FIRRTL_BEFORE_INITIAL
`FIRRTL_BEFORE_INITIAL
`endif
initial begin
  `ifdef RANDOMIZE
    `ifdef INIT_RANDOM
      `INIT_RANDOM
    `endif
    `ifndef VERILATOR
      `ifdef RANDOMIZE_DELAY
        #`RANDOMIZE_DELAY begin end
      `else
        #0.002 begin end
      `endif
    `endif
`ifdef RANDOMIZE_REG_INIT
  _RAND_0 = {1{`RANDOM}};
  memReg_0 = _RAND_0[7:0];
  _RAND_1 = {1{`RANDOM}};
  memReg_1 = _RAND_1[7:0];
  _RAND_2 = {1{`RANDOM}};
  memReg_2 = _RAND_2[7:0];
  _RAND_3 = {1{`RANDOM}};
  memReg_3 = _RAND_3[7:0];
  _RAND_4 = {1{`RANDOM}};
  memReg_4 = _RAND_4[7:0];
  _RAND_5 = {1{`RANDOM}};
  memReg_5 = _RAND_5[7:0];
  _RAND_6 = {1{`RANDOM}};
  memReg_6 = _RAND_6[7:0];
  _RAND_7 = {1{`RANDOM}};
  memReg_7 = _RAND_7[7:0];
  _RAND_8 = {1{`RANDOM}};
  memReg_8 = _RAND_8[7:0];
  _RAND_9 = {1{`RANDOM}};
  memReg_9 = _RAND_9[7:0];
  _RAND_10 = {1{`RANDOM}};
  wrptr = _RAND_10[4:0];
  _RAND_11 = {1{`RANDOM}};
  rdptr = _RAND_11[4:0];
`endif // RANDOMIZE_REG_INIT
  `endif // RANDOMIZE
end // initial
`ifdef FIRRTL_AFTER_INITIAL
`FIRRTL_AFTER_INITIAL
`endif
`endif // SYNTHESIS
endmodule

fifo/test_run_dir/DUT_should_pass/syncFifo.vcd
$date
2024-01-12T12:48+0000
$end
$version
0.2
$end
$comment

$end
$timescale 1ns  $end
$scope module syncFifo $end
 $var wire 1 ! io_full $end
 $var wire 8 " memReg_8 $end
 $var wire 8 # io_WriteInterface_bits $end
 $var wire 1 $ io_WriteInterface_ready $end
 $var wire 8 % memReg_7 $end
 $var wire 8 & memReg_1 $end
 $var wire 8 ' memReg_4 $end
 $var wire 1 ( io_ReadInterface_valid $end
 $var wire 8 ) memReg_3 $end
 $var wire 8 * memReg_6 $end
 $var wire 1 + ren $end
 $var wire 1 , clock $end
 $var wire 8 - memReg_0 $end
 $var wire 8 . memReg_9 $end
 $var wire 5 / rdptr $end
 $var wire 4 0 io_cnt $end
 $var wire 8 1 io_ReadInterface_bits $end
 $var wire 1 2 io_WriteInterface_valid $end
 $var wire 5 3 wrptr $end
 $var wire 8 4 memReg_2 $end
 $var wire 1 5 reset $end
 $var wire 1 6 io_empty $end
 $var wire 1 7 wen $end
 $var wire 1 8 io_ReadInterface_ready $end
 $var wire 8 9 memReg_5 $end
$upscope $end
$enddefinitions $end
$dumpvars
05
b00000000 )
b00000 3
b00000000 "
b00000000 1
b0000 0
b00000000 #
06
0!
b00000000 *
b00000000 9
0(
07
b00000 /
08
b00000000 -
b00000000 %
b00000000 4
0+
b00000000 &
02
0,
0$
b00000000 '
b00000000 .
$end
#0
15
16
1$
#1
1,
#6
05
0,
#11
1,
#16
0,
#21
1,
#26
12
17
0,
#31
b00001 3
b0001 0
06
1(
1,
#36
18
02
1+
07
0,
#41
b0000 0
16
0+
0(
b00001 /
1,
#46
08
0,
#51
1,
#56
b00000001 #
12
17
0,
#61
b00010 3
b0001 0
b00000001 1
b00000001 &
06
1(
1,
#66
18
02
1+
07
0,
#71
b0000 0
b00000000 1
16
0+
0(
b00010 /
1,
#76
b00000010 #
12
17
0,
#81
b00011 3
b0001 0
b00000010 4
b00000010 1
06
1+
1(
1,
#86
02
07
0,
#91
b0000 0
b00000000 1
16
0+
0(
b00011 /
1,
#96
08
0,
#101
1,
#106
0,
#111
1,
#116
0,
#121
1,
#126
0,
#131
1,
#136
b00000011 #
12
17
0,
#141
b00100 3
b0001 0
b00000011 1
06
1(
1,
b00000011 )
#146
18
02
1+
07
0,
#151
b0000 0
b00000000 1
16
0+
0(
b00100 /
1,
#156
08
b00000100 #
12
17
0,
#161
b00101 3
b0001 0
b00000100 1
b00000100 '
06
1(
1,
#166
18
02
1+
07
0,
#171
b0000 0
b00000000 1
16
0+
0(
b00101 /
1,
#176
b00000101 #
12
17
0,
#181
b00110 3
b0001 0
b00000101 1
b00000101 9
06
1+
1(
1,
#186
08
b00000110 #
0+
0,
#191
b00111 3
b0010 0
b00000110 *
1,
#196
02
07
0,
#201
1,
#206
18
b00000111 #
12
1+
17
0,
#211
b01000 3
b00000111 %
b00000110 1
b00110 /
1,
#216
b00001000 #
0,
#221
b01001 3
b00001000 "
b00000111 1
b00111 /
1,
#226
08
02
0+
07
0,
#231
1,
#236
0,
#241
1,
#246
18
1+
0,
#251
b0001 0
b00001000 1
b01000 /
1,
#256
08
0+
0,
#261
1,
#266
18
b00001001 #
12
1+
17
0,
#271
b10000 3
b0000 0
b00001001 1
b00001001 .
16
0+
0(
b01001 /
1,
#276
02
07
0,
#281
1,
#286
08
0,
#291
1,
#296
0,
#301
1,
#306
0,
#311
1,
#316
b00001010 #
12
17
0,
#321
b10001 3
b0001 0
b00001010 -
06
1(
1,
#326
18
02
1+
07
0,
#331
b00001010 1
b10000 /
1,
#336
08
0+
0,
#341
1,
#346
0,
#351
1,
#356
b00001011 #
12
17
0,
#361
b10010 3
b0010 0
b00001011 &
1,
#366
18
02
1+
07
0,
#371
b0001 0
b00001011 1
b10001 /
1,
#376
08
b00001100 #
12
0+
17
0,
#381
b10011 3
b0010 0
b00001100 4
1,
#386
18
02
1+
07
0,
#391
b0001 0
b00001100 1
b10010 /
1,
#396
b00001101 #
12
17
0,
#401
b10100 3
b00001101 1
b10011 /
1,
b00001101 )
#406
08
02
0+
07
0,
#411
1,
#416
18
b00001110 #
12
1+
17
0,
#421
b10101 3
b00001110 1
b00001110 '
b10100 /
1,
#426
08
b00001111 #
0+
0,
#431
b10110 3
b0010 0
b00001111 9
1,
#436
02
07
0,
#441
1,
#446
18
b00010000 #
12
1+
17
0,
#451
b10111 3
b00001111 1
b00010000 *
b10101 /
1,
#456
08
02
0+
07
0,
#461
1,
#466
18
1+
0,
#471
b0001 0
b00010000 1
b10110 /
1,
#476
0,
#481
b0000 0
b00000111 1
16
0+
0(
b10111 /
1,
#486
b00010001 #
12
17
0,
#491
b11000 3
b0001 0
b00010001 %
b00010001 1
06
1+
1(
1,
#496
02
07
0,
#501
b0000 0
b00001000 1
16
0+
0(
b11000 /
1,
#506
0,
#511
1,
#516
b00010010 #
12
17
0,
#521
b11001 3
b0001 0
b00010010 "
b00010010 1
06
1+
1(
1,
#526
08
b00010011 #
0+
0,
#531
b00000 3
b00010011 .
1,
#536
18
02
1+
07
0,
#541
b0000 0
b00010011 1
16
0+
0(
b11001 /
1,
#546
b00010100 #
12
17
0,
#551
b00001 3
b0001 0
b00010100 -
06
1+
1(
1,
#556
08
b00010101 #
0+
0,
#561
b00010 3
b0010 0
b00010101 &
1,
#566
02
07
0,
#571
1,
#576
0,
#581
1,
#586
18
b00010110 #
12
1+
17
0,
#591
b00011 3
b0011 0
b00010110 4
b00010100 1
b00000 /
1,
#596
b00010111 #
0,
#601
b00100 3
b00010101 1
b00001 /
1,
b00010111 )
#606
08
b00011000 #
0+
0,
#611
b00101 3
b0100 0
b00011000 '
1,
#616
18
b00011001 #
1+
0,
#621
b00110 3
b00010110 1
b00011001 9
b00010 /
1,
#626
08
02
0+
07
0,
#631
1,
#636
18
1+
0,
#641
b0011 0
b00010111 1
b00011 /
1,
#646
08
b00011010 #
12
0+
17
0,
#651
b00111 3
b0100 0
b00011010 *
1,
#656
18
b00011011 #
1+
0,
#661
b01000 3
b00011011 %
b00011000 1
b00100 /
1,
#666
02
07
0,
#671
b0011 0
b00011001 1
b00101 /
1,
#676
08
0+
0,
#681
1,
#686
18
b00011100 #
12
1+
17
0,
#691
b01001 3
b00011100 "
b00011010 1
b00110 /
1,
#696
02
07
0,
#701
b0010 0
b00011011 1
b00111 /
1,
#706
08
0+
0,
#711
1,
#716
0,
#721
1,
#726
18
1+
0,
#731
b0001 0
b00011100 1
b01000 /
1,
#736
08
b00011101 #
12
0+
17
0,
#741
b10000 3
b00011101 .
1,
#746
02
07
0,
#751
1,
#756
b00011110 #
12
17
0,
#761
b10001 3
b0010 0
b00011110 -
1,
#766
02
07
0,
#771
1,
#776
18
1+
0,
#781
b0001 0
b00011101 1
b01001 /
1,
#786
0,
#791
b00011110 1
b10000 /
1,
#796
0,
#801
b0000 0
b00010101 1
16
0+
0(
b10001 /
1,
#806
b00011111 #
12
17
0,
#811
b10010 3
b0001 0
b00011111 1
b00011111 &
06
1+
1(
1,
#816
b00100000 #
0,
#821
b10011 3
b00100000 4
b00100000 1
b10010 /
1,
#826
08
02
0+
07
0,
#831
1,
#836
b00100001 #
12
17
0,
#841
b10100 3
b0010 0
1,
b00100001 )
#846
02
07
0,
#851
1,
#856
0,
#861
1,
#866
18
1+
0,
#871
b0001 0
b00100001 1
b10011 /
1,
#876
08
0+
0,
#881
1,
#886
0,
#891
1,
#896
0,
#901
1,
#906
18
b00100010 #
12
1+
17
0,
#911
b10101 3
b00100010 1
b00100010 '
b10100 /
1,
#916
08
02
0+
07
0,
#921
1,
#926
b00100011 #
12
17
0,
#931
b10110 3
b0010 0
b00100011 9
1,
#936
b00100100 #
0,
#941
b10111 3
b0011 0
b00100100 *
1,
#946
18
02
1+
07
0,
#951
b0010 0
b00100011 1
b10101 /
1,
#956
0,
#961
b0001 0
b00100100 1
b10110 /
1,
#966
08
b00100101 #
12
0+
17
0,
#971
b11000 3
b0010 0
b00100101 %
1,
#976
02
07
0,
#981
1,
#986
18
1+
0,
#991
b0001 0
b00100101 1
b10111 /
1,
#996
0,
#1001
b0000 0
b00011100 1
16
0+
0(
b11000 /
1,
#1006
0,
#1011
1,
#1016
08
b00100110 #
12
17
0,
#1021
b11001 3
b0001 0
b00100110 "
b00100110 1
06
1(
1,
#1026
18
b00100111 #
1+
0,
#1031
b00000 3
b0000 0
b00100111 1
b00100111 .
16
0+
0(
b11001 /
1,
#1036
08
02
07
0,
#1041
1,
#1046
0,
#1051
1,
#1056
0,
#1061
1,
#1066
b00101000 #
12
17
0,
#1071
b00001 3
b0001 0
b00101000 -
06
1(
1,
#1076
18
b00101001 #
1+
0,
#1081
b00010 3
b0010 0
b00101000 1
b00101001 &
b00000 /
1,
#1086
02
07
0,
#1091
b0001 0
b00101001 1
b00001 /
1,
#1096
0,
#1101
b0000 0
b00100000 1
16
0+
0(
b00010 /
1,
#1106
0,
#1111
1,
#1116
0,
#1121
1,
#1126
08
0,
#1131
1,
#1136
0,
#1141
1,
#1146
b00101010 #
12
17
0,
#1151
b00011 3
b0001 0
b00101010 4
b00101010 1
06
1(
1,
#1156
18
02
1+
07
0,
#1161
b0000 0
b00100001 1
16
0+
0(
b00011 /
1,
#1166
08
b00101011 #
12
17
0,
#1171
b00100 3
b0001 0
b00101011 1
06
1(
1,
b00101011 )
#1176
18
b00101100 #
1+
0,
#1181
b00101 3
b00101100 1
b00101100 '
b00100 /
1,
#1186
08
b00101101 #
0+
0,
#1191
b00110 3
b0010 0
b00101101 9
1,
#1196
18
b00101110 #
1+
0,
#1201
b00111 3
b00101101 1
b00101110 *
b00101 /
1,
#1206
08
02
0+
07
0,
#1211
1,
#1216
0,
#1221
1,
#1226
0,
#1231
1,
#1236
18
1+
0,
#1241
b0001 0
b00101110 1
b00110 /
1,
#1246
b00101111 #
12
17
0,
#1251
b01000 3
b00101111 %
b00101111 1
b00111 /
1,
#1256
02
07
0,
#1261
b0000 0
b00100110 1
16
0+
0(
b01000 /
1,
#1266
08
0,
#1271
1,
#1276
0,
#1281
1,
#1286
b00110000 #
12
17
0,
#1291
b01001 3
b0001 0
b00110000 "
b00110000 1
06
1(
1,
#1296
02
07
0,
#1301
1,
#1306
0,
#1311
1,
#1316
b00110001 #
12
17
0,
#1321
b10000 3
b00110001 .
1,
#1326
18
02
1+
07
0,
#1331
b0000 0
b00110001 1
16
0+
0(
b01001 /
1,
#1336
b00110010 #
12
17
0,
#1341
b10001 3
b0001 0
b00110010 -
06
1+
1(
1,
#1346
b00110011 #
0,
#1351
b10010 3
b0010 0
b00110010 1
b00110011 &
b10000 /
1,
#1356
08
02
0+
07
0,
#1361
1,
#1366
b00110100 #
12
17
0,
#1371
b10011 3
b0011 0
b00110100 4
1,
#1376
b00110101 #
0,
#1381
b10100 3
b0100 0
1,
b00110101 )
#1386
02
07
0,
#1391
1,
#1396
18
b00110110 #
12
1+
17
0,
#1401
b10101 3
b00110011 1
b00110110 '
b10001 /
1,
#1406
b00110111 #
0,
#1411
b10110 3
b00110100 1
b00110111 9
b10010 /
1,
#1416
08
02
0+
07
0,
#1421
1,
#1426
18
1+
0,
#1431
b0011 0
b00110101 1
b10011 /
1,
#1436
08
b00111000 #
12
0+
17
0,
#1441
b10111 3
b0100 0
b00111000 *
1,
#1446
18
b00111001 #
1+
0,
#1451
b11000 3
b00111001 %
b00110110 1
b10100 /
1,
#1456
08
02
0+
07
0,
#1461
1,
#1466
18
1+
0,
#1471
b0011 0
b00110111 1
b10101 /
1,
#1476
08
0+
0,
#1481
1,
#1486
18
1+
0,
#1491
b0010 0
b00111000 1
b10110 /
1,
#1496
08
b00111010 #
12
0+
17
0,
#1501
b11001 3
b0011 0
b00111010 "
1,
#1506
02
07
0,
#1511
1,
#1516
b00111011 #
12
17
0,
#1521
b00000 3
b00111011 .
1,
#1526
b00111100 #
0,
#1531
b00001 3
b0100 0
b00111100 -
1,
#1536
18
02
1+
07
0,
#1541
b0011 0
b00111001 1
b10111 /
1,
#1546
b00111101 #
12
17
0,
#1551
b00010 3
b00111010 1
b00111101 &
b11000 /
1,
#1556
08
02
0+
07
0,
#1561
1,
#1566
18
b00111110 #
12
1+
17
0,
#1571
b00011 3
b00111110 4
b00111011 1
b11001 /
1,
#1576
08
02
0+
07
0,
#1581
1,
#1586
18
b00111111 #
12
1+
17
0,
#1591
b00100 3
b0100 0
b00111100 1
b00000 /
1,
b00111111 )
#1596
08
b01000000 #
0+
0,
#1601
b00101 3
b0101 0
b01000000 '
1,
#1606
02
07
0,
#1611
1,
#1616
0,
#1621
1,
#1626
18
b01000001 #
12
1+
17
0,
#1631
b00110 3
b00111101 1
b01000001 9
b00001 /
1,
#1636
02
07
0,
#1641
b0100 0
b00111110 1
b00010 /
1,
#1646
b01000010 #
12
17
0,
#1651
b00111 3
b00111111 1
b01000010 *
b00011 /
1,
#1656
08
b01000011 #
0+
0,
#1661
b01000 3
b0101 0
b01000011 %
1,
#1666
b01000100 #
0,
#1671
b01001 3
b0110 0
b01000100 "
1,
#1676
02
07
0,
#1681
1,
#1686
0,
#1691
1,
#1696
0,
#1701
1,
#1706
18
1+
0,
#1711
b0101 0
b01000000 1
b00100 /
1,
#1716
08
0+
0,
#1721
1,
#1726
18
1+
0,
#1731
b0100 0
b01000001 1
b00101 /
1,
#1736
08
b01000101 #
12
0+
17
0,
#1741
b10000 3
b01000101 .
1,
#1746
18
02
1+
07
0,
#1751
b0011 0
b01000010 1
b00110 /
1,
#1756
08
0+
0,
#1761
1,
#1766
0,
#1771
1,
#1776
0,
#1781
1,
#1786
0,
#1791
1,
#1796
0,
#1801
1,
#1806
18
b01000110 #
12
1+
17
0,
#1811
b10001 3
b01000110 -
b01000011 1
b00111 /
1,
#1816
02
07
0,
#1821
b0010 0
b01000100 1
b01000 /
1,
#1826
08
b01000111 #
12
0+
17
0,
#1831
b10010 3
b0011 0
b01000111 &
1,
#1836
b01001000 #
0,
#1841
b10011 3
b0100 0
b01001000 4
1,
#1846
02
07
0,
#1851
1,
#1856
18
1+
0,
#1861
b0011 0
b01000101 1
b01001 /
1,
#1866
b01001001 #
12
17
0,
#1871
b10100 3
b0100 0
b01000110 1
b10000 /
1,
b01001001 )
#1876
08
b01001010 #
0+
0,
#1881
b10101 3
b0101 0
b01001010 '
1,
#1886
b01001011 #
0,
#1891
b10110 3
b0110 0
b01001011 9
1,
#1896
02
07
0,
#1901
1,
#1906
0,
#1911
1,
#1916
b01001100 #
12
17
0,
#1921
b10111 3
b0111 0
b01001100 *
1,
#1926
b01001101 #
0,
#1931
b11000 3
b1000 0
b01001101 %
1,
#1936
02
07
0,
#1941
1,
#1946
0,
#1951
1,
#1956
18
1+
0,
#1961
b0111 0
b01000111 1
b10001 /
1,
#1966
b01001110 #
12
17
0,
#1971
b11001 3
b01001110 "
b01001000 1
b10010 /
1,
#1976
b01001111 #
0,
#1981
b00000 3
b0110 0
b01001001 1
b01001111 .
b10011 /
1,
#1986
08
b01010000 #
0+
0,
#1991
b00001 3
b0111 0
b01010000 -
1,
#1996
b01010001 #
0,
#2001
b00010 3
b1000 0
b01010001 &
1,
#2006
02
07
0,
#2011
1,
#2016
0,
#2021
1,
#2026
18
1+
0,
#2031
b0111 0
b01001010 1
b10100 /
1,
#2036
08
0+
0,
#2041
1,
#2046
b01010010 #
12
17
0,
#2051
b00011 3
b1000 0
b01010010 4
1,
#2056
18
02
1+
07
0,
#2061
b0111 0
b01001011 1
b10101 /
1,
#2066
b01010011 #
12
17
0,
#2071
b00100 3
b01001100 1
b10110 /
1,
b01010011 )
#2076
b01010100 #
0,
#2081
b00101 3
b01001101 1
b01010100 '
b10111 /
1,
#2086
02
07
0,
#2091
b0110 0
b01001110 1
b11000 /
1,
#2096
08
b01010101 #
12
0+
17
0,
#2101
b00110 3
b0111 0
b01010101 9
1,
#2106
b01010110 #
0,
#2111
b00111 3
b1000 0
b01010110 *
1,
#2116
02
07
0,
#2121
1,
#2126
0,
#2131
1,
#2136
0,
#2141
1,
#2146
0,
#2151
1,
#2156
0,
#2161
1,
#2166
18
b01010111 #
12
1+
17
0,
#2171
b01000 3
b01010111 %
b01001111 1
b11001 /
1,
#2176
b01011000 #
0,
#2181
b01001 3
b1001 0
1!
b01011000 "
b01010000 1
0$
07
b00000 /
1,
#2186
02
0,
#2191
0!
b1000 0
b01010001 1
1$
b00001 /
1,
#2196
b01011001 #
12
17
0,
#2201
b10000 3
b0111 0
b01010010 1
b01011001 .
b00010 /
1,
#2206
08
b01011010 #
0+
0,
#2211
b10001 3
b1000 0
b01011010 -
1,
#2216
18
b01011011 #
1+
0,
#2221
b10010 3
b01010011 1
b01011011 &
b00011 /
1,
#2226
08
b01011100 #
0+
0,
#2231
b10011 3
b1001 0
1!
b01011100 4
0$
07
1,
#2236
0,
#2241
1,
#2246
0,
#2251
1,
#2256
0,
#2261
1,
#2266
18
02
1+
0,
#2271
0!
b1000 0
b01010100 1
1$
b00100 /
1,
#2276
0,
#2281
b0111 0
b01010101 1
b00101 /
1,
#2286
08
0+
0,
#2291
1,
#2296
0,
#2301
1,
#2306
0,
#2311
1,
#2316
18
1+
0,
#2321
b0110 0
b01010110 1
b00110 /
1,
#2326
0,
#2331
b0101 0
b01010111 1
b00111 /
1,
#2336
08
0+
0,
#2341
1,
#2346
b01011101 #
12
17
0,
#2351
b10100 3
b0110 0
1,
b01011101 )
#2356
b01011110 #
0,
#2361
b10101 3
b0111 0
b01011110 '
1,
#2366
02
07
0,
#2371
1,
#2376
18
b01011111 #
12
1+
17
0,
#2381
b10110 3
b01011000 1
b01011111 9
b01000 /
1,
#2386
08
02
0+
07
0,
#2391
1,
#2396
18
1+
0,
#2401
b0110 0
b01011001 1
b01001 /
1,
#2406
08
0+
0,
#2411
1,
#2416
b01100000 #
12
17
0,
#2421
b10111 3
b0111 0
b01100000 *
1,
#2426
18
b01100001 #
1+
0,
#2431
b11000 3
b1000 0
b01100001 %
b01011010 1
b10000 /
1,
#2436
08
b01100010 #
0+
0,
#2441
b11001 3
b1001 0
1!
b01100010 "
0$
07
1,
#2446
02
0,
#2451
1,
#2456
18
1+
0,
#2461
0!
b1000 0
b01011011 1
1$
b10001 /
1,
#2466
08
b01100011 #
12
0+
17
0,
#2471
b00000 3
b01100011 .
1,
#2476
b01100100 #
0,
#2481
b00001 3
b1001 0
b01100100 -
1!
0$
07
1,
#2486
18
1+
0,
#2491
0!
b1000 0
b01011100 1
1$
17
b10010 /
1,
#2496
08
02
0+
07
0,
#2501
1,
#2506
18
1+
0,
#2511
b0111 0
b01011101 1
b10011 /
1,
#2516
b01100101 #
12
17
0,
#2521
b00010 3
b01011110 1
b01100101 &
b10100 /
1,
#2526
02
07
0,
#2531
b0110 0
b01011111 1
b10101 /
1,
#2536
08
b01100110 #
12
0+
17
0,
#2541
b00011 3
b0111 0
b01100110 4
1,
#2546
18
b01100111 #
1+
0,
#2551
b00100 3
b01100000 1
b10110 /
1,
b01100111 )
#2556
08
b01101000 #
0+
0,
#2561
b00101 3
b1000 0
b01101000 '
1,
#2566
02
07
0,
#2571
1,
#2576
18
1+
0,
#2581
b0111 0
b01100001 1
b10111 /
1,
#2586
08
0+
0,
#2591
1,
#2596
b01101001 #
12
17
0,
#2601
b00110 3
b1000 0
b01101001 9
1,
#2606
02
07
0,
#2611
1,
#2616
0,
#2621
1,
#2626
b01101010 #
12
17
0,
#2631
b00111 3
b1001 0
1!
b01101010 *
0$
07
1,
#2636
18
1+
0,
#2641
0!
b1000 0
b01100010 1
1$
17
b11000 /
1,
#2646
08
02
0+
07
0,
#2651
1,
#2656
18
1+
0,
#2661
b0111 0
b01100011 1
b11001 /
1,
#2666
b01101011 #
12
17
0,
#2671
b01000 3
b1000 0
b01101011 %
b01100100 1
b00000 /
1,
#2676
08
02
0+
07
0,
#2681
1,
#2686
18
b01101100 #
12
1+
17
0,
#2691
b01001 3
b01101100 "
b01100101 1
b00001 /
1,
#2696
08
02
0+
07
0,
#2701
1,
#2706
b01101101 #
12
17
0,
#2711
b10000 3
b01101101 .
1,
#2716
18
02
1+
07
0,
#2721
b0111 0
b01100110 1
b00010 /
1,
#2726
08
b01101110 #
12
0+
17
0,
#2731
b10001 3
b1000 0
b01101110 -
1,
#2736
18
02
1+
07
0,
#2741
b0111 0
b01100111 1
b00011 /
1,
#2746
b01101111 #
12
17
0,
#2751
b10010 3
b01101000 1
b01101111 &
b00100 /
1,
#2756
b01110000 #
0,
#2761
b10011 3
b01110000 4
b01101001 1
b00101 /
1,
#2766
08
02
0+
07
0,
#2771
1,
#2776
0,
#2781
1,
#2786
0,
#2791
1,
#2796
0,
#2801
1,
#2806
18
b01110001 #
12
1+
17
0,
